stemtrace/__init__.py
stemtrace/py.typed
stemtrace/core/__init__.py
stemtrace/core/events.py
stemtrace/core/exceptions.py
stemtrace/core/graph.py
stemtrace/core/ports.py
stemtrace/library/__init__.py
stemtrace/library/bootsteps.py
stemtrace/library/config.py
stemtrace/library/scrubbing.py
stemtrace/library/signals.py
stemtrace/library/transports/__init__.py
stemtrace/library/transports/memory.py
stemtrace/library/transports/rabbitmq.py
stemtrace/library/transports/redis.py
stemtrace/server/__init__.py
stemtrace/server/__main__.py
stemtrace/server/consumer.py
stemtrace/server/store.py
stemtrace/server/websocket.py
stemtrace/server/api/__init__.py
stemtrace/server/api/routes.py
stemtrace/server/api/schemas.py
stemtrace/server/api/websocket.py
stemtrace/server/fastapi/__init__.py
stemtrace/server/fastapi/auth.py
stemtrace/server/fastapi/extension.py
stemtrace/server/fastapi/form_auth.py
stemtrace/server/fastapi/login_routes.py
stemtrace/server/fastapi/router.py
stemtrace/server/ui/__init__.py
stemtrace/server/ui/static.py
stemtrace/server/ui/frontend/biome.json
stemtrace/server/ui/frontend/index.html
stemtrace/server/ui/frontend/package-lock.json
stemtrace/server/ui/frontend/package.json
stemtrace/server/ui/frontend/playwright.config.ts
stemtrace/server/ui/frontend/postcss.config.js
stemtrace/server/ui/frontend/tsconfig.json
stemtrace/server/ui/frontend/tsconfig.tsbuildinfo
stemtrace/server/ui/frontend/vite.config.ts
stemtrace/server/ui/frontend/dist/index.html
stemtrace/server/ui/frontend/dist/assets/index-CuKk6f1B.css
stemtrace/server/ui/frontend/dist/assets/index-DynKlZ8o.js
stemtrace/server/ui/frontend/src/index.css
stemtrace/server/ui/frontend/src/main.tsx
stemtrace/server/ui/frontend/src/vite-env.d.ts
stemtrace/server/ui/frontend/src/api/client.ts
stemtrace/server/ui/frontend/src/api/queries.ts
stemtrace/server/ui/frontend/src/components/DateRangePicker.tsx
stemtrace/server/ui/frontend/src/components/Filters.tsx
stemtrace-0.3.1.dist-info/METADATA
stemtrace-0.3.1.dist-info/WHEEL
stemtrace-0.3.1.dist-info/entry_points.txt
stemtrace-0.3.1.dist-info/licenses/LICENSE
stemtrace-0.3.1.dist-info/RECORD
