Metadata-Version: 2.4
Name: stemtrace
Version: 0.3.1
Summary: A lightweight Celery task flow visualizer
Project-URL: Homepage, https://github.com/iansokolskyi/stemtrace
Project-URL: Documentation, https://github.com/iansokolskyi/stemtrace#readme
Project-URL: Repository, https://github.com/iansokolskyi/stemtrace
Project-URL: Issues, https://github.com/iansokolskyi/stemtrace/issues
Project-URL: Changelog, https://github.com/iansokolskyi/stemtrace/blob/main/CHANGELOG.md
Author-email: Ian Sokolskyi <iansokolskyi@gmail.com>
Maintainer-email: Ian Sokolskyi <iansokolskyi@gmail.com>
License: MIT
License-File: LICENSE
Keywords: celery,monitoring,queue,task,visualization,workflow
Classifier: Development Status :: 3 - Alpha
Classifier: Environment :: Console
Classifier: Environment :: Web Environment
Classifier: Framework :: Celery
Classifier: Intended Audience :: Developers
Classifier: License :: OSI Approved :: MIT License
Classifier: Operating System :: OS Independent
Classifier: Programming Language :: Python :: 3
Classifier: Programming Language :: Python :: 3.10
Classifier: Programming Language :: Python :: 3.11
Classifier: Programming Language :: Python :: 3.12
Classifier: Programming Language :: Python :: 3.13
Classifier: Programming Language :: Python :: 3.14
Classifier: Topic :: Software Development :: Libraries :: Python Modules
Classifier: Topic :: System :: Monitoring
Classifier: Typing :: Typed
Requires-Python: >=3.10
Requires-Dist: celery>=5.0.0
Requires-Dist: fastapi>=0.100.0
Requires-Dist: httpx>=0.24.0
Requires-Dist: pydantic>=2.0.0
Requires-Dist: redis>=4.0.0
Requires-Dist: typer>=0.9.0
Requires-Dist: typing-extensions>=4.0.0
Requires-Dist: uvicorn[standard]>=0.20.0
Provides-Extra: dev
Requires-Dist: build>=1.0.0; extra == 'dev'
Requires-Dist: bump-my-version>=0.28.0; extra == 'dev'
Requires-Dist: hatchling>=1.20.0; extra == 'dev'
Requires-Dist: mypy>=1.0.0; extra == 'dev'
Requires-Dist: pre-commit>=3.0.0; extra == 'dev'
Requires-Dist: pytest-asyncio>=0.21.0; extra == 'dev'
Requires-Dist: pytest-cov>=4.0.0; extra == 'dev'
Requires-Dist: pytest>=7.0.0; extra == 'dev'
Requires-Dist: ruff>=0.1.0; extra == 'dev'
Requires-Dist: twine>=5.0.0; extra == 'dev'
Requires-Dist: types-redis>=4.0.0; extra == 'dev'
Requires-Dist: websockets>=12.0; extra == 'dev'
